test_updates/__init__.py
test_updates/test_updates.py
test_updates-1.dist-info/METADATA
test_updates-1.dist-info/WHEEL
test_updates-1.dist-info/top_level.txt
test_updates-1.dist-info/RECORD
