Metadata-Version: 2.1
Name: test-updates
Version: 1
Summary: Writing style analyzer
Home-page: UNKNOWN
Author: Ekaterina Levitskaya, Kara Kedrick, Russell J. Funk
Author-email: test_test@email.com, test_test1@email.com, test_test_1@email.com
License: UNKNOWN
Keywords: python,writing style
Platform: UNKNOWN
Classifier: Development Status :: 3 - Alpha
Classifier: Intended Audience :: Education
Classifier: Programming Language :: Python :: 2
Classifier: Programming Language :: Python :: 3
Classifier: Operating System :: MacOS :: MacOS X
Classifier: Operating System :: Microsoft :: Windows
Requires-Dist: spacy
